benhw/__init__.py
benhw/benhw.py
benhw/exceptions.py
benhw/tokens.py
benhw/dlls/IEEE_32M.dll
benhw/dlls/IEEE_32M_KPCI-488A.dll
benhw/dlls/IEEE_32M_KUSB-488A.dll
benhw/dlls/IEEE_32M_NI_VISA.dll
benhw/dlls/IEEE_32M_keithley.dll
benhw/dlls/benhw32_cdecl.dll
benhw/dlls/benhw64.dll
benhw-0.1.0.dist-info/METADATA
benhw-0.1.0.dist-info/WHEEL
benhw-0.1.0.dist-info/top_level.txt
benhw-0.1.0.dist-info/RECORD
